README.md
linkml_tutorial_2024/_version.py
linkml_tutorial_2024/datamodel/__init__.py
linkml_tutorial_2024/datamodel/linkml_tutorial_2024.py
linkml_tutorial_2024/datamodel/pydanticmodel_v2.py
linkml_tutorial_2024/schema/linkml_tutorial_2024.yaml
linkml_tutorial_2024-0.0.2.dist-info/LICENSE
linkml_tutorial_2024-0.0.2.dist-info/METADATA
linkml_tutorial_2024-0.0.2.dist-info/WHEEL
linkml_tutorial_2024-0.0.2.dist-info/RECORD
