Metadata-Version: 2.1
Name: linkml_tutorial_2024
Version: 0.0.2
Summary: A repostitory that walks through schema generation.
License: MIT
Author: LinkML Team
Author-email: admin@linkml.org
Requires-Python: >=3.9,<4.0
Classifier: License :: OSI Approved :: MIT License
Classifier: Programming Language :: Python :: 3
Classifier: Programming Language :: Python :: 3.9
Classifier: Programming Language :: Python :: 3.10
Classifier: Programming Language :: Python :: 3.11
Classifier: Programming Language :: Python :: 3.12
Provides-Extra: docs
Requires-Dist: linkml-runtime (>=1.1.24,<2.0.0)
